signac_dashboard/__init__.py
signac_dashboard/__main__.py
signac_dashboard/dashboard.py
signac_dashboard/module.py
signac_dashboard/pagination.py
signac_dashboard/util.py
signac_dashboard/version.py
signac_dashboard/views.py
signac_dashboard/modules/__init__.py
signac_dashboard/modules/document_editor.py
signac_dashboard/modules/document_list.py
signac_dashboard/modules/file_list.py
signac_dashboard/modules/flow_status.py
signac_dashboard/modules/image_viewer.py
signac_dashboard/modules/navigator.py
signac_dashboard/modules/notes.py
signac_dashboard/modules/schema.py
signac_dashboard/modules/statepoint_list.py
signac_dashboard/modules/text_display.py
signac_dashboard/modules/video_viewer.py
signac_dashboard/static/.gitignore
signac_dashboard/static/images/favicon.ico
signac_dashboard/static/images/favicon.png
signac_dashboard/static/js/jquery-3.6.4.min.js
signac_dashboard/static/js/js_all/bulma-modal-fx.js
signac_dashboard/static/js/js_all/menu-toggle-mobile.js
signac_dashboard/static/js/js_all/nprogress.js
signac_dashboard/static/js/js_all/nprogress_config.js
signac_dashboard/static/js/js_all/turbolinks.js
signac_dashboard/static/scss/_morris.scss
signac_dashboard/static/scss/_nprogress.scss
signac_dashboard/static/scss/app.scss
signac_dashboard/static/scss/bulma/.editorconfig
signac_dashboard/static/scss/bulma/.git
signac_dashboard/static/scss/bulma/.gitignore
signac_dashboard/static/scss/bulma/.travis.yml
signac_dashboard/static/scss/bulma/BACKERS.md
signac_dashboard/static/scss/bulma/CHANGELOG.md
signac_dashboard/static/scss/bulma/LICENSE
signac_dashboard/static/scss/bulma/README.md
signac_dashboard/static/scss/bulma/bower.json
signac_dashboard/static/scss/bulma/bulma.sass
signac_dashboard/static/scss/bulma/favicon.ico
signac_dashboard/static/scss/bulma/package-lock.json
signac_dashboard/static/scss/bulma/package.json
signac_dashboard/static/scss/bulma/yarn.lock
signac_dashboard/static/scss/bulma/.github/CONTRIBUTING.md
signac_dashboard-0.6.1.dist-info/LICENSE.txt
signac_dashboard-0.6.1.dist-info/METADATA
signac_dashboard-0.6.1.dist-info/WHEEL
signac_dashboard-0.6.1.dist-info/entry_points.txt
signac_dashboard-0.6.1.dist-info/top_level.txt
signac_dashboard-0.6.1.dist-info/RECORD
