Metadata-Version: 2.1
Name: signac-dashboard
Version: 0.6.1
Summary: Visualize data spaces in a web browser.
Author-email: "Bradley Dice et al." <bdice@bradleydice.com>
Maintainer-email: signac Developers <signac-support@umich.edu>
License: BSD 3-Clause License for the software signac-dashboard.
Project-URL: Homepage, https://signac.io
Project-URL: Documentation, https://docs.signac.io
Project-URL: Download, https://pypi.org/project/signac-dashboard/
Project-URL: Source, https://github.com/glotzerlab/signac-dashboard
Project-URL: Issues, https://github.com/glotzerlab/signac-dashboard/issues
Keywords: visualization,dashboard,signac,framework
Classifier: Development Status :: 4 - Beta
Classifier: Intended Audience :: Science/Research
Classifier: License :: OSI Approved :: BSD License
Classifier: Topic :: Database
Classifier: Topic :: Scientific/Engineering :: Physics
Classifier: Programming Language :: Python :: 3.8
Classifier: Programming Language :: Python :: 3.9
Classifier: Programming Language :: Python :: 3.10
Classifier: Programming Language :: Python :: 3.11
Classifier: Programming Language :: Python :: 3.12
Requires-Python: >=3.8
License-File: LICENSE.txt
Requires-Dist: flask >=2.1.0
Requires-Dist: flask-assets >=2.0.0
Requires-Dist: flask-login >=0.6.1
Requires-Dist: flask-turbolinks
Requires-Dist: jinja2 >=3.0.0
Requires-Dist: jsmin
Requires-Dist: libsass
Requires-Dist: markupsafe >=2.0.0
Requires-Dist: natsort
Requires-Dist: signac >=2.0.0
Requires-Dist: watchdog
Requires-Dist: webassets >=2.0.0
Requires-Dist: werkzeug >=2.1.0
